LICENSE
MANIFEST.in
README.md
requirements.txt
setup.py
aiohttp_login/__init__.py
aiohttp_login/asyncpg_storage.py
aiohttp_login/cfg.py
aiohttp_login/decorators.py
aiohttp_login/flash.py
aiohttp_login/forms.py
aiohttp_login/handlers.py
aiohttp_login/motor_storage.py
aiohttp_login/oauth.py
aiohttp_login/pg_tables.sql
aiohttp_login/sql.py
aiohttp_login/utils.py
aiohttp_login.egg-info/PKG-INFO
aiohttp_login.egg-info/SOURCES.txt
aiohttp_login.egg-info/dependency_links.txt
aiohttp_login.egg-info/requires.txt
aiohttp_login.egg-info/top_level.txt
aiohttp_login/templates/bootstrap-3/base.html
aiohttp_login/templates/bootstrap-3/change_email.html
aiohttp_login/templates/bootstrap-3/change_password.html
aiohttp_login/templates/bootstrap-3/confirmation_error.html
aiohttp_login/templates/bootstrap-3/flash.html
aiohttp_login/templates/bootstrap-3/login.html
aiohttp_login/templates/bootstrap-3/macroses.html
aiohttp_login/templates/bootstrap-3/registration.html
aiohttp_login/templates/bootstrap-3/registration_requested.html
aiohttp_login/templates/bootstrap-3/reset_password.html
aiohttp_login/templates/bootstrap-3/reset_password_allowed.html
aiohttp_login/templates/bootstrap-3/reset_password_requested.html
aiohttp_login/templates/bootstrap-3/social_auth_buttons.html
aiohttp_login/templates/bootstrap-3/styles.html
aiohttp_login/templates/bootstrap-4/base.html
aiohttp_login/templates/bootstrap-4/change_email.html
aiohttp_login/templates/bootstrap-4/change_password.html
aiohttp_login/templates/bootstrap-4/confirmation_error.html
aiohttp_login/templates/bootstrap-4/flash.html
aiohttp_login/templates/bootstrap-4/login.html
aiohttp_login/templates/bootstrap-4/macroses.html
aiohttp_login/templates/bootstrap-4/registration.html
aiohttp_login/templates/bootstrap-4/registration_requested.html
aiohttp_login/templates/bootstrap-4/reset_password.html
aiohttp_login/templates/bootstrap-4/reset_password_allowed.html
aiohttp_login/templates/bootstrap-4/reset_password_requested.html
aiohttp_login/templates/bootstrap-4/social_auth_buttons.html
aiohttp_login/templates/bootstrap-4/styles.html
aiohttp_login/templates/common/change_email_email.html
