Metadata-Version: 1.1
Name: aiohttp-login
Version: 1.4.0
Summary: Registration and authorization (including social) for aiohttp apps
Home-page: https://github.com/imbolc/aiohttp-login
Author: Imbolc
Author-email: imbolc@imbolc.name
License: ISC
Platform: UNKNOWN
Classifier: Development Status :: 4 - Beta
Classifier: Intended Audience :: Developers
Classifier: License :: OSI Approved :: ISC License (ISCL)
Classifier: Programming Language :: Python
Classifier: Programming Language :: Python :: 3
